src/mcp_tools_cli.py
mcp_tools_cli-0.1.0.dist-info/METADATA
mcp_tools_cli-0.1.0.dist-info/WHEEL
mcp_tools_cli-0.1.0.dist-info/entry_points.txt
mcp_tools_cli-0.1.0.dist-info/licenses/LICENSE
mcp_tools_cli-0.1.0.dist-info/RECORD
