Metadata-Version: 2.4
Name: mcp-tools-cli
Version: 0.1.0
Summary: command-line client for interacting with Model Context Protocol (MCP) servers.
Author-email: moritalous <moritalous@gmail.com>
License: MIT License
License-File: LICENSE
Requires-Python: >=3.12
Requires-Dist: mcp>=1.5.0
